{"collectible": true, "set": "JOURNEY_TO_UNGORO", "name": "Chittering Tunneler", "heroClass": "WARLOCK", "description": "Battlecry: Discover a spell. Deal damage to your hero equal to its Cost.", "fileFormatVersion": 1, "rarity": "EPIC", "baseHp": 3, "race": "BEAST", "baseAttack": 3, "attributes": {"BATTLECRY": true}, "battlecry": {"spell": {"cardFilter": {"cardType": "SPELL", "class": "CardFilter"}, "spell": {"targetPlayer": "SELF", "spell": {"targetPlayer": "SELF", "class": "DamageSpell", "value": {"attribute": "BASE_MANA_COST", "class": "AttributeValueProvider", "target": "EVENT_CARD"}, "target": "FRIENDLY_HERO"}, "class": "ReceiveCardAndDoSomethingSpell"}, "class": "DiscoverRandomCardSpell"}, "targetSelection": "NONE"}, "type": "MINION", "baseManaCost": 3}