{
  "name": "Grim Harvest",
  "baseManaCost": 7,
  "type": "SPELL",
  "heroClass": "BLOOD",
  "rarity": "RARE",
  "description": "Drain 5 Health from the central enemy unit (or units). Receive a copy of any that die.",
  "targetSelection": "NONE",
  "spell": {
    "class": "ConditionalEffectSpell",
    "target": "ENEMY_MIDDLE_MINIONS",
    "condition": {
      "class": "IsDeadCondition"
    },
    "spell1": {
      "class": "DrainSpell",
      "value": 5
    },
    "spell2": {
      "class": "CopyCardSpell"
    }
  },
  "attributes": {
    "DRAIN": true
  },
  "collectible": false,
  "fileFormatVersion": 1,
  "sets": [
    "CUSTOM",
    "CLASSIC"
  ]
}