{
  "name": "Bittertide Crab",
  "baseManaCost": 1,
  "type": "MINION",
  "heroClass": "ANY",
  "baseAttack": 1,
  "baseHp": 2,
  "rarity": "EPIC",
  "race": "BEAST",
  "description": "Opener: Destroy 5 Armor from a player to gain +1/+1.",
  "battlecry": {
    "targetSelection": "HEROES",
    "spell": {
      "class": "MetaSpell",
      "filter": {
        "class": "AttributeFilter",
        "value": 5,
        "attribute": "ARMOR",
        "operation": "GREATER_OR_EQUAL"
      },
      "spells": [
        {
          "class": "BuffSpell",
          "armorBonus": -5
        },
        {
          "class": "BuffSpell",
          "target": "SELF",
          "attackBonus": 1,
          "hpBonus": 1
        }
      ]
    }
  },
  "attributes": {
    "BATTLECRY": true
  },
  "collectible": true,
  "set": "CUSTOM",
  "fileFormatVersion": 1
}
