{
  "name": "Mass Conscription",
  "baseManaCost": 2,
  "type": "HERO_POWER",
  "heroClass": "GOLD",
  "rarity": "FREE",
  "description": "Summon two 1/1 Recruits.",
  "condition": {
    "class": "MinionCountCondition",
    "value": 7,
    "operation": "LESS"
  },
  "targetSelection": "NONE",
  "spell": {
    "class": "SummonSpell",
    "cards": [
      "token_silver_hand_recruit",
      "token_silver_hand_recruit"
    ]
  },
  "collectible": false,
  "set": "THE_GRAND_TOURNAMENT",
  "fileFormatVersion": 1
}