{
  "seed" : -730019199581070154,
  "catalogueVersion" : 1,
  "heroClasses" : [ "NEONGREEN", "GOLD" ],
  "deckCardIds" : [ [ "spell_feeding_frenzy", "spell_malignancy", "minion_corpse_raiser", "minion_recurring_torrent", "spell_cull_and_reap", "minion_safeguard", "spell_warp", "permanent_formless_rancour", "spell_cellular_overdrive", "spell_cull_and_reap", "permanent_formless_immortal", "spell_xenobulwark", "minion_silver_warmaiden", "minion_lowly_squire", "minion_mecharoo", "minion_death_s_messenger", "minion_archmage", "minion_warclub_ruffian", "minion_silver_vanguard", "minion_force-tank_max", "spell_primordial_supremacy", "minion_hecklebot", "spell_observer", "spell_primordial_supremacy", "spell_observer", "spell_feeding_frenzy", "minion_mind_harvester", "spell_cannibalize", "spell_chaos_bolts", "minion_primordial_drake" ], [ "spell_prismatic_aspect", "spell_a_new_challenger...", "minion_glass_memory_golem", "minion_chillwind_yeti", "spell_desperate_stand", "minion_tentacle_of_nzoth", "spell_enter_the_coliseum", "minion_deepwood_barghest", "minion_kobold_monk", "spell_seal_of_champions", "spell_consecration", "minion_pompous_thespian", "minion_grimestreet_smuggler", "minion_trigger_happy_survivor", "minion_secretkeeper", "spell_divine_favor", "minion_friendly_bartender", "spell_call_to_arms", "minion_hot_garbage", "minion_former_champ", "minion_aegwynn", "minion_grimestreet_smuggler", "minion_venomancer", "minion_high_priest_thekal", "minion_muck_hunter", "spell_forever_a_student", "spell_lesser_pearl_spellstone", "spell_silvermoon_portal", "spell_shield_of_the_righteous", "minion_batterhead" ] ],
  "deckFormatName" : "Custom",
  "deckFormatSets" : [ "KNIGHTS_OF_THE_FROZEN_THRONE", "LEAGUE_OF_EXPLORERS", "MEAN_STREETS_OF_GADGETZAN", "THE_OLD_GODS", "CUSTOM", "VERDANT_DREAMS", "JOURNEY_TO_UNGORO", "THE_GRAND_TOURNAMENT", "BATTLE_FOR_ASHENVALE", "CLASSIC", "BLACKROCK_MOUNTAIN", "BASIC", "BOOMSDAY_PROJECT", "KOBOLDS_AND_CATACOMBS", "RASTAKHANS_RUMBLE", "PROMO", "HALL_OF_FAME", "ONE_NIGHT_IN_KARAZHAN", "RISE_OF_SHADOWS", "REWARD", "NAXXRAMAS", "SPELLSOURCE_BASIC", "SANDS_OF_TIME", "GOBLINS_VS_GNOMES", "WITCHWOOD" ],
  "mulligans" : [ [ 9, 33, 8 ], [ 63, 60 ] ],
  "actions" : [ 0, 2, 0, 0, 3, 0, 2, 4, 0, 8, 0, 1, 0, 0, 2, 0, 0, 5, 0, 1, 9, 3, 0, 0, 2, 1, 2, 6, 2, 2, 2, 1, 3, 0, 0, 10, 2, 0, 0, 15, 0, 0, 0, 10, 3, 11, 3, 22, 27, 22, 3 ],
  "id" : null
}