{
  "seed" : 7152072964834320907,
  "catalogueVersion" : 2,
  "heroClasses" : [ "LEATHER", "TEAL" ],
  "deckCardIds" : [ [ "minion_wink_dog", "minion_harbinger_of_hope", "minion_holdout_soldier", "spell_focus_fire", "minion_tree_giant", "quest_forge_it", "minion_rakanishu", "minion_jungle_operative", "minion_infinite_behemoth", "weapon_sharp_a_practice", "minion_eranikus", "spell_amber_drop", "minion_wild_pyrodancer", "spell_demand", "spell_countershot", "minion_whizbang_the_plunderful", "spell_party_poppers", "minion_captain_of_the_guard", "minion_primalist_kirra", "spell_triple_shot", "minion_augmented_pixie", "minion_drakonid_brute", "spell_new_arrival", "spell_dead_or_alive", "minion_zarmull_the_silent_mercenary", "spell_party_poppers", "minion_ninja_aspirants", "minion_mr_smith", "spell_supply", "minion_alemental" ], [ "minion_tidal_rager", "minion_squirrel_knight", "minion_aberrant_tinyfin", "spell_calm_currents", "minion_perplexed_courtsman", "minion_storm_giant", "weapon_cerith_scepter", "minion_nazjatar_seahorseman", "minion_brawler_bushi", "minion_champion_of_death", "minion_murloc_jek", "minion_lord_cookie", "minion_shadownest_arachne", "spell_water_blast", "weapon_brine_crossbolter", "minion_aberrant_tinyfin", "minion_dimensional_courier", "minion_nice_cream", "spell_they_came_from_below", "minion_throat_cutter", "spell_evaporation", "spell_regal_gaze", "minion_wolfcrier", "weapon_serpentcrest_staff", "minion_dante_the_outlaw", "weapon_cerith_scepter", "spell_squid_ward", "minion_n_zoth_s_battlemaiden", "minion_ninja_aspirants", "weapon_saltspring_wand" ] ],
  "deckFormatName" : "Spellsource",
  "deckFormatSets" : [ "VERDANT_DREAMS", "SANDS_OF_TIME", "BATTLE_FOR_ASHENVALE", "CUSTOM", "SPELLSOURCE_BASIC" ],
  "secondPlayerBonusCards" : [ "spell_lunstone" ],
  "mulligans" : [ [ 17, 9, 25 ], [ 40, 65, 64 ] ],
  "actions" : [ 0, 1, 1, 0, 0, 0, 0, 2, 0, 2, 0, 7, 0 ],
  "id" : null
}