{
  "name": "Grandmaster Hun",
  "heroPower": "hero_power_light_of_hope",
  "baseManaCost": 8,
  "type": "HERO",
  "heroClass": "JADE",
  "rarity": "LEGENDARY",
  "description": "Battlecry: Summon all Students to the field.",
  "battlecry": {
    "targetSelection": "NONE",
    "spell": {
      "class": "SummonSpell",
      "cards": [
        "minion_student_of_the_crane",
        "minion_student_of_the_ox",
        "minion_student_of_the_serpent",
        "minion_student_of_the_tiger"
      ]
    }
  },
  "attributes": {
    "ARMOR": 5,
    "BATTLECRY": true,
    "MAX_HP": 30
  },
  "collectible": true,
  "set": "CUSTOM",
  "fileFormatVersion": 1
}
