{
	"name": "Corpse Explosion",
	"baseManaCost": 2,
	"type": "SPELL",
	"heroClass": "HUNTER",
	"rarity": "EPIC",
	"description": "Secret: When one of your minions dies, deal it's Attack damage to all enemy minions.",
	"race": "SURVIVAL",
	"trigger": {
		"class": "MinionDeathTrigger",
		"targetPlayer": "SELF"
	},
	"spell": {
		"class": "DamageSpell",
		"target": "ENEMY_MINIONS",
		"value": {
			"class": "AttributeValueProvider",
			"target": "EVENT_TARGET",
			"attribute": "ATTACK"
		}
	},
	"instant": {
		"targetSelection": "FRIENDLY_MINIONS",
		"spell": {
			"class": "DamageSpell",
			"target": "ENEMY_MINIONS",
			"value": {
				"class": "AttributeValueProvider",
				"target": "TARGET",
				"attribute": "ATTACK"
			}
		}
	},
	"collectible": true,
	"set": "CUSTOM",
	"fileFormatVersion": 1
}