{
  "name": "Cry Wolf",
  "baseManaCost": 2,
  "type": "SPELL",
  "heroClass": "GREEN",
  "rarity": "RARE",
  "description": "Echo. Summon a 1/1 Sheep. Future copies this turn summon a 3/3 Wolf.",
  "targetSelection": "NONE",
  "spell": {
    "class": "EitherOrSpell",
    "spell1": {
      "class": "SummonSpell",
      "card": "token_wolf"
    },
    "spell2": {
      "class": "SummonSpell",
      "card": "token_sheep"
    },
    "condition": {
      "class": "AttributeCondition",
      "target": "SELF",
      "attribute": "REMOVES_SELF_AT_END_OF_TURN",
      "operation": "HAS"
    }
  },
  "attributes": {
    "ECHO": true
  },
  "collectible": true,
  "set": "CUSTOM",
  "fileFormatVersion": 1
}