{
  "name": "Kobold Illusionist",
  "baseManaCost": 4,
  "type": "MINION",
  "heroClass": "BLACK",
  "baseAttack": 3,
  "baseHp": 3,
  "rarity": "RARE",
  "description": "Deathrattle: Summon a 1/1 copy of a minion from your hand.",
  "deathrattle": {
    "class": "SummonSpell",
    "target": "FRIENDLY_HAND",
    "spell": {
      "class": "MetaSpell",
      "target": "OUTPUT",
      "spells": [
        {
          "class": "SetAttributeSpell",
          "value": 1,
          "attribute": "BASE_ATTACK"
        },
        {
          "class": "SetAttributeSpell",
          "value": 1,
          "attribute": "ATTACK"
        },
        {
          "class": "SetAttributeSpell",
          "value": 1,
          "attribute": "BASE_HP"
        },
        {
          "class": "SetAttributeSpell",
          "value": 1,
          "attribute": "HP"
        }
      ]
    },
    "filter": {
      "class": "CardFilter",
      "cardType": "MINION"
    },
    "randomTarget": true
  },
  "attributes": {
    "DEATHRATTLES": true
  },
  "collectible": true,
  "set": "KOBOLDS_AND_CATACOMBS",
  "fileFormatVersion": 1
}