{
  "name": "Frenzied Diabolist",
  "baseManaCost": 2,
  "type": "MINION",
  "heroClass": "VIOLET",
  "baseAttack": 2,
  "baseHp": 2,
  "rarity": "COMMON",
  "description": "Battlecry: Discover a card you discarded this game.",
  "battlecry": {
    "targetSelection": "NONE",
    "spell": {
      "class": "DiscoverSpell",
      "spell": {
        "class": "ReceiveCardSpell",
        "targetPlayer": "SELF"
      },
      "cardFilter": {
        "class": "AttributeFilter",
        "attribute": "DISCARDED",
        "operation": "HAS"
      },
      "cardSource": {
        "class": "GraveyardCardsSource",
        "distinct": true,
        "targetPlayer": "SELF"
      }
    }
  },
  "attributes": {
    "BATTLECRY": true
  },
  "collectible": true,
  "set": "CUSTOM",
  "fileFormatVersion": 1
}