{
  "name": "Animation Surge",
  "baseManaCost": 2,
  "type": "SPELL",
  "heroClass": "EGGPLANT",
  "rarity": "COMMON",
  "description": "Summon three 1/1 Golems. Invoke (5): Summon five instead.",
  "targetSelection": "NONE",
  "spell": {
    "class": "SummonSpell",
    "value": {
      "class": "ConditionalValueProvider",
      "condition": {
        "class": "InvokeCondition"
      },
      "ifFalse": 3,
      "ifTrue": 5
    },
    "card": "token_rock_golem"
  },
  "attributes": {
    "INVOKE": 5
  },
  "collectible": true,
  "set": "CUSTOM",
  "fileFormatVersion": 1
}