{
  "name": "Macabre Samaritan",
  "baseManaCost": 9,
  "type": "MINION",
  "heroClass": "ANY",
  "baseAttack": 6,
  "baseHp": 12,
  "rarity": "FREE",
  "description": "Whenever this takes damage, restore #4 Health to your champion.",
  "trigger": {
    "eventTrigger": {
      "class": "DamageReceivedTrigger",
      "hostTargetType": "IGNORE_OTHER_TARGETS"
    },
    "spell": {
      "class": "HealSpell",
      "target": "FRIENDLY_HERO",
      "value": 4
    }
  },
  "collectible": true,
  "set": "SPELLSOURCE_BASIC",
  "fileFormatVersion": 1
}