{
  "name": "Bloodthirst",
  "baseManaCost": 3,
  "type": "SPELL",
  "heroClass": "WARRIOR",
  "rarity": "RARE",
  "race": "FURY",
  "description": "Give your minions 'Enrage: +3 Attack'.",
  "targetSelection": "NONE",
  "spell": {
    "class": "MetaSpell",
    "target": "FRIENDLY_MINIONS",
    "spells": [
      {
        "class": "AddEnchantmentSpell",
        "trigger": {
          "eventTrigger": {
            "class": "EnrageChangedTrigger"
          },
          "spell": {
            "class": "EnrageSpell",
            "target": "SELF"
          }
        }
      },
      {
        "class": "AddAttributeSpell",
        "attribute": "ENRAGABLE"
      },
      {
        "class": "ModifyAttributeSpell",
        "value": 3,
        "attribute": "ENRAGED_ATTACK",
        "operation": "ADD"
      },
      {
        "class": "ConditionalSpell",
        "condition": {
          "class": "IsDamagedCondition"
        },
        "spell": {
          "class": "MetaSpell",
          "spells": [
            {
              "class": "AddAttributeSpell",
              "attribute": "ENRAGED"
            },
            {
              "class": "EnrageSpell"
            }
          ]
        }
      }
    ]
  },
  "collectible": true,
  "set": "CUSTOM",
  "fileFormatVersion": 1
}