{
  "name": "Gilnean Tracker",
  "baseManaCost": 3,
  "type": "MINION",
  "heroClass": "ANY",
  "baseAttack": 3,
  "baseHp": 3,
  "rarity": "FREE",
  "description": "<b>Rush</b> At the start of your turn, transform this into a 5/5.",
  "trigger": {
    "eventTrigger": {
      "class": "TurnStartTrigger",
      "targetPlayer": "SELF"
    },
    "spell": {
      "class": "TransformMinionSpell",
      "target": "SELF",
      "card": "token_transforming_tracker"
    }
  },
  "attributes": {
    "RUSH": true
  },
  "collectible": false,
  "set": "WITCHWOOD",
  "fileFormatVersion": 1
}