{
	"name": "Revitalizer",
	"baseManaCost": 2,
	"type": "MINION",
	"baseAttack": 2,
	"baseHp": 3,
	"heroClass": "ANY",
	"rarity": "COMMON",
	"description": "Battlecry: Fully heal a friendly minion",
	"battlecry": {
		"targetSelection": "FRIENDLY_MINIONS",
		"spell": {
			"class": "HealSpell",
			"value": {
				"class": "AttributeValueProvider",
				"target": "TARGET",
				"attribute": "MAX_HP"
			}
		}
	},
	"attributes": {
		"BATTLECRY": true
	},
	"collectible": true,
	"set": "SANDS_OF_TIME",
	"fileFormatVersion": 1
}