{
  "name": "Earthshake",
  "baseManaCost": 7,
  "type": "SPELL",
  "heroClass": "LIGHTBROWN",
  "rarity": "FREE",
  "description": "Deal $2 damage to all enemy units. Draw 2 cards",
  "targetSelection": "NONE",
  "spell": {
    "class": "MetaSpell",
    "spells": [
      {
        "class": "DamageSpell",
        "target": "ENEMY_MINIONS",
        "value": 2
      },
      {
        "class": "DrawCardSpell",
        "value": 2
      }
    ]
  },
  "collectible": true,
  "sets": [
    "CUSTOM",
    "BASIC"
  ],
  "fileFormatVersion": 1
}