{
  "name": "Menacing Dragotron",
  "baseManaCost": 5,
  "type": "MINION",
  "heroClass": "RUST",
  "baseAttack": 3,
  "baseHp": 4,
  "rarity": "RARE",
  "race": "MECH",
  "description": "Deathrattle: Destroy all minions with less Attack than this minion.",
  "deathrattle": {
    "class": "DestroySpell",
    "target": "ALL_MINIONS",
    "filter": {
      "class": "AttributeFilter",
      "value": {
        "class": "AttributeValueProvider",
        "target": "SELF",
        "attribute": "ATTACK"
      },
      "attribute": "ATTACK",
      "operation": "LESS"
    }
  },
  "attributes": {
    "DEATHRATTLES": true
  },
  "collectible": true,
  "set": "CUSTOM",
  "fileFormatVersion": 1
}