{
  "name": "Coldsteel Blade",
  "baseManaCost": 6,
  "type": "WEAPON",
  "heroClass": "RUST",
  "damage": 5,
  "durability": 3,
  "rarity": "EPIC",
  "description": "Supremacy: Summon a 4/4 Dragon",
  "trigger": {
    "eventTrigger": {
      "class": "SupremacyTrigger"
    },
    "spell": {
      "class": "SupremacySpell",
      "spell": {
        "class": "SummonSpell",
        "card": "token_44dragon",
        "targetPlayer": "SELF"
      }
    }
  },
  "attributes": {
    "SUPREMACY": true
  },
  "collectible": false,
  "set": "CUSTOM",
  "fileFormatVersion": 1
}