{
  "name": "The 4th Ring Warden",
  "baseManaCost": 4,
  "type": "MINION",
  "heroClass": "BLUEGREY",
  "baseAttack": 4,
  "baseHp": 3,
  "rarity": "LEGENDARY",
  "race": "DEMON",
  "description": "Opener: If your deck has no duplicates, your played minions are reborn as 2/2 Lesser Oni this game.",
  "battlecry": {
    "targetSelection": "NONE",
    "condition": {
      "class": "HighlanderDeckCondition"
    },
    "spell": {
      "class": "AddEnchantmentSpell",
      "target": "FRIENDLY_PLAYER",
      "trigger": {
        "eventTrigger": {
          "class": "AfterMinionPlayedTrigger",
          "targetPlayer": "SELF"
        },
        "spell": {
          "class": "AddDeathrattleSpell",
          "target": "EVENT_TARGET",
          "spell": {
            "class": "SummonSpell",
            "card": "token_lesser_oni"
          }
        },
        "exclusive": true #Check changes description
      }
    }
  },
  "attributes": {
    "BATTLECRY": true
  },
  "collectible": true,
  "set": "CUSTOM",
  "fileFormatVersion": 1
}
