{
  "name": "Open the Waygate",
  "baseManaCost": 1,
  "type": "SPELL",
  "heroClass": "MAGE",
  "rarity": "LEGENDARY",
  "description": "Quest: Cast 6 spells on your minions. Reward: Galvadon",
  "targetSelection": "NONE",
  "quest": {
    "class": "TargetAcquisitionTrigger",
    "sourcePlayer": "SELF",
    "actionType": "SPELL",
    "targetEntityType": "MINION",
    "targetPlayer": "SELF",
    "queueCondition": {
      "class": "OwnedByPlayerCondition",
      "target": "EVENT_TARGET",
      "targetPlayer": "SELF"
    }
  },
  "countUntilCast": 6,
  "spell": {
    "class": "ReceiveCardSpell",
    "card": "token_galvadon"
  },
  "collectible": true,
  "set": "JOURNEY_TO_UNGORO",
  "fileFormatVersion": 1
}