{
  "name": "Gobble",
  "baseManaCost": 2,
  "type": "SPELL",
  "heroClass": "RUST",
  "rarity": "COMMON",
  "description": "Destroy the lowest Attack enemy unit on the battlefield.",
  "targetSelection": "NONE",
  "spell": {
    "class": "DestroySpell",
    "target": "ENEMY_MINIONS",
    "filter": {
      "class": "AttributeFilter",
      "value": {
        "class": "ReduceValueProvider",
        "target": "ENEMY_MINIONS",
        "operation": "MINIMUM",
        "value1": {
          "class": "AttributeValueProvider",
          "attribute": "ATTACK"
        }
      },
      "attribute": "ATTACK",
      "operation": "EQUAL"
    },
    "randomTarget": true
  },
  "attributes": {},
  "collectible": true,
  "sets": [
    "CUSTOM",
    "CORE"
  ],
  "fileFormatVersion": 1
}