{
  "name": "Doomlord Urc",
  "baseManaCost": 5,
  "type": "MINION",
  "heroClass": "NAVY",
  "baseAttack": 2,
  "baseHp": 8,
  "rarity": "LEGENDARY",
  "description": "Opener: Gain your minions' enchantments (WIP).",
  "battlecry": {
    "targetSelection": "NONE",
    "spell": {
      "class": "custom.CopyEnchantmentsSpell",
      "target": "SELF",
      "secondaryTarget": "OTHER_FRIENDLY_MINIONS"
    }
  },
  "attributes": {
    "BATTLECRY": true
  },
  "collectible": false,
  "set": "CUSTOM",
  "fileFormatVersion": 1
}