{
  "name": "Recruit Barracks",
  "baseManaCost": 4,
  "type": "MINION",
  "heroClass": "CRIMSON",
  "baseAttack": 0,
  "baseHp": 3,
  "rarity": "RARE",
  "description": "Stealth for 1 turn. At the end of your turn, summon a 2/2 Captive.",
  "trigger": {
    "eventTrigger": {
      "class": "TurnEndTrigger",
      "targetPlayer": "SELF"
    },
    "spell": {
      "class": "SummonSpell",
      "boardPositionRelative": "RIGHT",
      "card": "token_captive_overlord"
    }
  },
  "attributes": {
    "STEALTH": true,
    "STEALTH_FOR_TURNS": 1
  },
  "collectible": true,
  "set": "CUSTOM",
  "fileFormatVersion": 1
}