{
  "name": "Red Crane Statue",
  "baseManaCost": 2,
  "type": "MINION",
  "heroClass": "JADE",
  "baseAttack": 0,
  "baseHp": 4,
  "rarity": "RARE",
  "race": "ELEMENTAL",
  "description": "Whenever you summon a minion, give it +2 Health.",
  "trigger": {
    "eventTrigger": {
      "class": "MinionSummonedTrigger",
      "targetPlayer": "SELF"
    },
    "spell": {
      "class": "BuffSpell",
      "target": "EVENT_TARGET",
      "attackBonus": 0,
      "hpBonus": 2
    }
  },
  "collectible": false,
  "set": "CUSTOM",
  "fileFormatVersion": 1
}