{
  "name": "Roll",
  "baseManaCost": 2,
  "type": "SPELL",
  "heroClass": "JADE",
  "rarity": "COMMON",
  "description": "Return an allied minion to your hand. It keeps any enchantments.",
  "targetSelection": "FRIENDLY_MINIONS",
  "spell": {
    "class": "MetaSpell",
    "spells": [
      {
        "class": "AddAttributeSpell",
        "attribute": "KEEPS_ENCHANTMENTS"
      },
      {
        "class": "ReturnToHandWithEnchantmentsSpell"
      }
    ]
  },
  "collectible": false,
  "set": "CUSTOM",
  "fileFormatVersion": 1
}