{
  "name": "Puppeteer Senzaku",
  "heroPower": "hero_power_no_strings_on_me",
  "baseManaCost": 8,
  "type": "HERO",
  "heroClass": "ROSE",
  "rarity": "LEGENDARY",
  "description": "Battlecry: After an enemy minion dies this game, summon it.",
  "battlecry": {
    "targetSelection": "NONE",
    "spell": {
      "class": "AddEnchantmentSpell",
      "target": "FRIENDLY_PLAYER",
      "trigger": {
        "eventTrigger": {
          "class": "MinionDeathTrigger",
          "targetPlayer": "OPPONENT"
        },
        "spell": {
          "class": "ResurrectFromBothSpell",
          "targetPlayer": "SELF",
          "cardFilter": {
            "class": "AndFilter",
            "filters": [
              {
                "class": "OwnedByPlayerFilter",
                "targetPlayer": "OPPONENT"
              },
              {
                "class": "SpecificCardFilter",
                "secondaryTarget": "EVENT_TARGET"
              }
            ]
          }
        }
      }
    }
  },
  "attributes": {
    "ARMOR": 5,
    "BATTLECRY": true,
    "MAX_HP": 30
  },
  "collectible": true,
  "set": "CUSTOM",
  "fileFormatVersion": 1
}