{
  "name": "Witch's Apprentice",
  "baseManaCost": 1,
  "type": "MINION",
  "heroClass": "SILVER",
  "baseAttack": 0,
  "baseHp": 1,
  "rarity": "COMMON",
  "race": "BEAST",
  "description": "Taunt. Battlecry: Add a random Shaman spell to your hand.",
  "battlecry": {
    "targetSelection": "NONE",
    "spell": {
      "class": "ReceiveCardSpell",
      "value": 1,
      "cardFilter": {
        "class": "CardFilter",
        "heroClass": "SILVER",
        "cardType": "SPELL"
      },
      "cardSource": {
        "class": "UnweightedCatalogueSource"
      }
    }
  },
  "attributes": {
    "BATTLECRY": true,
    "TAUNT": true
  },
  "collectible": true,
  "set": "WITCHWOOD",
  "fileFormatVersion": 1
}