{
  "name": "Thitazov",
  "baseManaCost": 6,
  "type": "MINION",
  "heroClass": "RUST",
  "baseAttack": 4,
  "baseHp": 4,
  "rarity": "LEGENDARY",
  "race": "DRAGON",
  "description": "At the end of your turns, give your other units +1/+1 and restore them to full Health.",
  "trigger": {
    "eventTrigger": {
      "class": "TurnEndTrigger",
      "targetPlayer": "SELF"
    },
    "spell": {
      "class": "MetaSpell",
      "target": "OTHER_FRIENDLY_MINIONS",
      "spells": [
        {
          "class": "BuffSpell",
          "value": 1
        },
        {
          "class": "HealSpell",
          "value": {
            "class": "AttributeValueProvider",
            "attribute": "MAX_HP"
          }
        }
      ]
    }
  },
  "attributes": {},
  "collectible": true,
  "set": "CUSTOM",
  "fileFormatVersion": 1
}