{
  "name": "Damaged Stegotron",
  "baseManaCost": 6,
  "type": "MINION",
  "baseAttack": 5,
  "baseHp": 12,
  "heroClass": "ANY",
  "rarity": "COMMON",
  "race": "MECH",
  "description": "Taunt. Battlecry: Deal 6 damage to this minion.",
  "battlecry": {
    "targetSelection": "NONE",
    "spell": {
      "class": "DamageSpell",
      "target": "SELF",
      "value": 6
     }
  },
  "attributes": {
    "BATTLECRY": true,
    "TAUNT": true
  },
  "collectible": true,
  "set": "BOOMSDAY_PROJECT",
  "fileFormatVersion": 1
}
