{
  "name": "Faithful Lumi",
  "baseManaCost": 1,
  "type": "MINION",
  "baseAttack": 1,
  "baseHp": 1,
  "heroClass": "ANY",
  "rarity": "COMMON",
  "race": "MECH",
  "description": "Battlecry: Give a friendly Mech +1/+1",
  "battlecry": {
    "targetSelection": "FRIENDLY_MINIONS",
		"spell": {
			"class": "BuffSpell",
			"value": 1,
			"filter": {
				"class": "RaceFilter",
				"race": "MECH"
			}
		}
  },
  "attributes": {
    "BATTLECRY": true
  },
  "collectible": true,
  "set": "BOOMSDAY_PROJECT",
  "fileFormatVersion": 1
}
