{
	"id": "minion_swapmaster",
	"name": "Swapmaster",
	"baseManaCost": 3,
	"type": "MINION",
	"baseAttack": 0,
	"baseHp": 3,
	"heroClass": "ANY",
	"rarity": "RARE",
	"race": "MECH",
	"description": "At the end of your turn, swap this minion with a random one on the battlefield..",
	"trigger": {
		"eventTrigger": {
			"class": "TurnEndTrigger",
			"targetPlayer": "SELF"
		},
		"spell": {
			"class": "SwapMinionSpell",
			"target": "SELF"
		}
	},
	"collectible": false,
	"set": "MINIONATE",
	"fileFormatVersion": 1
}