{
  "name": "Double Next Battlecry",
  "type": "ENCHANTMENT",
  "heroClass": "ANY",
  "rarity": "FREE",
  "description": "The next battlecry played this turn is triggered twice.",
  "aura": {
    "class": "DoubleBattlecriesAura",
    "target": "FRIENDLY_CARDS"
  },
  "triggers": [
    {
      "eventTrigger": {
        "class": "BattlecryResolvedTrigger",
        "queueCondition": {
          "class": "CardPropertyCondition",
          "card": "minion_murmuring_elemental",
          "invert": true
        }
      },
      "spell": {
        "class": "RemoveEnchantmentSpell",
        "target": "TRIGGER_HOST",
        "card": "enchantment_double_next_battlecry"
      }
    },
    {
      "eventTrigger": {
        "class": "TurnEndTrigger",
        "targetPlayer": "SELF"
      },
      "spell": {
        "class": "RemoveEnchantmentSpell",
        "target": "TRIGGER_HOST",
        "card": "enchantment_double_next_battlecry"
      }
    }
  ],
  "collectible": false,
  "set": "KOBOLDS_AND_CATACOMBS",
  "fileFormatVersion": 1
}
