{
  "name": "Blood-Bound Golem",
  "baseManaCost": 5,
  "type": "MINION",
  "heroClass": "CRIMSON",
  "baseAttack": 4,
  "baseHp": 5,
  "rarity": "EPIC",
  "description": "<b>Guard</b>. Costs (3) if your champion took damage this turn.",
  "attributes": {
    "TAUNT": true
  },
  "collectible": true,
  "sets": [
    "CUSTOM",
    "CLASSIC"
  ],
  "fileFormatVersion": 1,
  "manaCostModifier": {
    "class": "ConditionalValueProvider",
    "condition": {
      "class": "AttributeCondition",
      "target": "FRIENDLY_PLAYER",
      "attribute": "DAMAGE_THIS_TURN",
      "value": 0,
      "operation": "GREATER"
    },
    "ifFalse": 0,
    "ifTrue": 2
  }
}