{
  "name": "Lesser Obsidian Lunstone",
  "baseManaCost": 2,
  "type": "SPELL",
  "heroClass": "OBSIDIAN",
  "rarity": "RARE",
  "description": "Give a random allied minion +2/+2. (Shuffle a card to upgrade)",
  "passiveTrigger": {
    "eventTrigger": {
      "class": "ShuffledTrigger",
      "hostTargetType": "IGNORE_AS_SOURCE",
      "queueCondition": {
        "class": "OwnedByPlayerCondition",
        "targetPlayer": "ACTIVE"
      }
    },
    "spell": {
      "class": "custom.TransformInHandSpell",
      "target": "SELF",
      "card": "spell_obsidian_spellstone"
    },
    "keepAfterTransform": false
  },
  "targetSelection": "NONE",
  "spell": {
    "class": "BuffSpell",
    "target": "FRIENDLY_MINIONS",
    "value": 2,
    "randomTarget": true
  },
  "collectible": true,
  "set": "CUSTOM",
  "fileFormatVersion": 1
}