{
  "name": "Hulking Chiroptid",
  "baseManaCost": 5,
  "type": "MINION",
  "heroClass": "BLOOD",
  "baseAttack": 4,
  "baseHp": 4,
  "rarity": "COMMON",
  "description": "Dash. Whenever this minion attacks, Drain 1 Health from the target.",
  "trigger": {
    "eventTrigger": {
      "class": "PhysicalAttackTrigger",
      "sourceEntityType": "MINION",
      "sourcePlayer": "SELF",
      "hostTargetType": "IGNORE_OTHER_SOURCES"
    },
    "spell": {
      "class": "DrainSpell",
      "target": "EVENT_TARGET",
      "value": 1
    }
  },
  "attributes": {
    "RUSH": true,
    "DRAIN": true
  },
  "collectible": false,
  "sets": [
    "CUSTOM",
    "VL_CRIMSONCATACOMBS"
  ],
  "fileFormatVersion": 1
}