{
  "name": "Snapshooter",
  "baseManaCost": 6,
  "type": "MINION",
  "heroClass": "LEATHER",
  "baseAttack": 7,
  "baseHp": 5,
  "rarity": "COMMON",
  "description": "Opener: Deal 4 damage to a Marked unit.",
  "battlecry": {
    "targetSelection": "ANY",
    "spell": {
      "class": "DamageSpell",
      "value": 4,
      "filter": {
        "class": "HasEnchantmentFilter",
        "card": "enchantment_marked"
      }
    }
  },
  "attributes": {
    "BATTLECRY": true
  },
  "collectible": true,
  "set": "CUSTOM",
  "fileFormatVersion": 1
}