{
  "name": "Awaken the Makers",
  "baseManaCost": 1,
  "type": "SPELL",
  "heroClass": "PRIEST",
  "rarity": "LEGENDARY",
  "description": "Quest: Summon 7 Deathrattle minions. Reward: Amara, Warden of Hope.",
  "quest": {
    "class": "MinionSummonedTrigger",
    "requiredAttribute": "DEATHRATTLES",
    "targetPlayer": "SELF"
  },
  "countUntilCast": 7,
  "targetSelection": "NONE",
  "spell": {
    "class": "ReceiveCardSpell",
    "card": "token_amara_warden_of_hope"
  },
  "collectible": true,
  "set": "JOURNEY_TO_UNGORO",
  "fileFormatVersion": 1
}