{
  "name": "For Science!",
  "baseManaCost": 4,
  "type": "SPELL",
  "heroClass": "DARKGREEN",
  "rarity": "RARE",
  "description": "Choose a minion. Whenever you play a minion this turn, give that minion +3/+3.",
  "targetSelection": "MINIONS",
  "spell": {
    "class": "AddEnchantmentSpell",
    "trigger": {
      "eventTrigger": {
        "class": "MinionSummonedTrigger",
        "targetPlayer": "SELF"
      },
      "spell": {
        "class": "BuffSpell",
        "target": "SELF",
        "value": 3
      },
      "oneTurn": true
    }
  },
  "fileFormatVersion": 1,
  "sets": [
    "CUSTOM",
    "KNIGHTS_OF_THE_FROZEN_THRONE"
  ]
}