{
	"id": "minion_healthy_spell",
	"name": "Healthy Spell",
	"baseManaCost": 6,
	"type": "MINION",
	"baseAttack": 5,
	"baseHp": 7,
	"heroClass": "ANY",
	"rarity": "FREE",
	"description": "Battlecry: If you have 15 or less Health, discover a spell.",
	"battlecry": {
		"targetSelection": "NONE",
		"spell": {
			"class": "DiscoverRandomCardSpell",
			"spell": {
				"class": "ReceiveCardSpell",
				"targetPlayer": "SELF"
			},
			"cardFilter": {
				"class": "CardFilter",
				"cardType": "SPELL"
			}
		},
		"condition": {
			"class": "AttributeCondition",
			"target": "FRIENDLY_HERO",
			"attribute": "HP",
			"operation": "LESS_OR_EQUAL",
			"value": 15
		}
	},
	"attributes": {
		"BATTLECRY": true
	},
	"collectible": true,
	"set": "Spellsource",
	"fileFormatVersion": 1
}